{
  "meta_title": "A Loja da Alice",
  "meta_description": "",
  "sections": [
    {
      "type": "banner-slider",
      "autoplay": 9000,
      "full_width": true,
      "slides": [
        {
          "start": "",
          "end": "",
          "img": "/img/uploads/img-20230112-wa0107.jpg"
        }
      ]
    },
    {
      "type": "info-bar",
      "enabled": true
    },
    {
      "type": "responsive-banner",
      "img": "/img/uploads/img-20221227-wa0007.jpg",
      "link": "https://alojadaalice.com.br/quero-ver-tudo"
    },
    {
      "type": "collection-shelf",
      "shuffle": true,
      "collection_id": null,
      "sort": "news",
      "title": "LANÇAMENTOS",
      "headless": true,
      "limit": 12,
      "page": 1
    },
    {
      "type": "collection-shelf",
      "shuffle": true,
      "limit": 12,
      "page": 1,
      "headless": true,
      "sort": "sales",
      "title": "MAIS VENDIDAS"
    },
    {
      "type": "responsive-banner",
      "img": "/img/uploads/img-20230112-wa0107.jpg",
      "mobile_img": "/img/uploads/20221227_192021_0000.png",
      "link": "https://alojadaalice.netlify.app/sale"
    },
    {
      "type": "collection-shelf",
      "shuffle": true,
      "limit": 12,
      "page": 1,
      "sort": "offers"
    },
    {
      "type": "page-title",
      "title": "",
      "description": ""
    }
  ]
}